disteval.py
disteval-0.3.dist-info/LICENSE
disteval-0.3.dist-info/METADATA
disteval-0.3.dist-info/WHEEL
disteval-0.3.dist-info/entry_points.txt
disteval-0.3.dist-info/top_level.txt
disteval-0.3.dist-info/RECORD
