Metadata-Version: 2.1
Name: disteval
Version: 0.3
Summary: DISTEVAL: For inter-residue protein distance evaluation
Home-page: https://github.com/ba-lab/disteval
Author: ba-lab
Author-email: adhikarib@umsl.edu
License: UNKNOWN
Platform: UNKNOWN
Classifier: Programming Language :: Python :: 3
Classifier: License :: OSI Approved :: MIT License
Requires-Dist: numpy
Requires-Dist: scikit-learn
